README.rst
__init__.py
api2.py
feed.py
fields.py
setup.py
version.py
wrapper.py
pyopenmensa.egg-info/PKG-INFO
pyopenmensa.egg-info/SOURCES.txt
pyopenmensa.egg-info/dependency_links.txt
pyopenmensa.egg-info/top_level.txt