Metadata-Version: 1.1
Name: pyopenmensa
Version: 0.90.2
Summary: Usefull python wrapper for creating OpenMensa feeds
Home-page: https://github.com/mswart/pyopenmensa
Author: Malte Swart
Author-email: mswart@devtation.de
License: LGPL
Keywords: openmensa feed framework
Platform: UNKNOWN
Classifier: Development Status :: 5 - Production/Stable
Classifier: Intended Audience :: Developers
Classifier: Topic :: Software Development :: Libraries
Classifier: License :: OSI Approved :: GNU Lesser General Public License v3 (LGPLv3)
Classifier: Programming Language :: Python :: 2
Classifier: Programming Language :: Python :: 2.6
Classifier: Programming Language :: Python :: 2.7
Classifier: Programming Language :: Python :: 3
Classifier: Programming Language :: Python :: 3.2
Classifier: Programming Language :: Python :: 3.3
Classifier: Programming Language :: Python :: 3.4
